[
    {
        "kind": "youtube#video",
        "etag": "blnodziRQCfVp2dMD9f9Im_W9-U",
        "id": "ff4ofql6kX8",
        "snippet": {
            "publishedAt": "2025-11-20T11:01:23Z",
            "channelId": "UCKyNmWAGzC-qhRxKg89Y9lg",
            "title": "\"Гений, Циник, Роковая женщина. В начале была игра\". МАЯКОВСКИЙ-БРИКИ. 1 серия @samamenshova",
            "description": "🎥Все серии МАЯКОВСКИЙ-БРИКИ https://www.youtube.com/playlist?list=PLLY5OYVYOkFbznJ15Jr6kKwABbgpL8jwb\n🎵 Альбом треков из сериала «Пожар сердца» https://zvonko.link/2077152\nИсполнитель — WWM// Маяк. Треки созданы полностью с помощью ИИ.\n\n«При вас этого бы не случилось!» — сказала мать Маяковского у гроба сына, обнимая Лилю и Осипа Брик, срочно вернувшихся из Берлина в Москву на похороны поэта. Неожиданно, правда? Кажется, современники, да и родные поэта, несколько иначе относились к этому знаменитому тройственному союзу, который сегодня принято исключительно клеймить. Так давайте вернемся к началу. Насколько справедливы ярлыки, приклеенные нами спустя 100 лет к его участникам? Лиля Брик — корыстная извращенка? Осип Брик — безвольный циник? Владимир Маяковский — доверчивый романтик?\nЖертвой коварной обольстительницы молодой поэт точно не был. Юный красавец и сам был горазд обольщать барышень из приличных семей, а потом бросать их, что с успехом проделал и в этот раз. Влюбившись в Лилю, он немедленно разорвал отношения с её родной сестрой Эльзой, хотя уже считался чуть ли не её женихом. Впрочем, сама Лиля к Маяковскому особого интереса не проявила, несмотря на потрясение его поэтическим талантом. Хотя она и заслужила репутацию femme fatale с ранних лет — её невероятное обаяние и манкость констатировали даже женщины, а мужчины и впрямь сходили с ума, — по иронии судьбы сама она всю жизнь смертельно любила лишь одного человека — собственного мужа. Но эта любовь не была взаимной…\nТайны и реальные подробности жизни самого скандального любовного треугольника XX века смотрите в нашем проекте «Маяковский — Брики. Володя. Лиля. Ося».\n\nСоцсети Юлии Меньшовой\nТелеграм: https://t.me/JuliaMenshovaJulia\nСообщество VK: https://vk.com/samamenshova\nRutube https://rutube.ru/u/samamenshova/\nЯндекс. Дзен: https://dzen.ru/samamenshova\nИнстаграм*: https://instagram.com/juliavmenshova\n\n#маяковский #брик #меньшова\n\n\n*Instagram — принадлежит американской компании Meta, которую признали экстремистской, запрещён на территории РФ.",
            "thumbnails": {
                "default": {
                    "url": "https://i.ytimg.com/vi/ff4ofql6kX8/default.jpg",
                    "width": 120,
                    "height": 90
                },
                "medium": {
                    "url": "https://i.ytimg.com/vi/ff4ofql6kX8/mqdefault.jpg",
                    "width": 320,
                    "height": 180
                },
                "high": {
                    "url": "https://i.ytimg.com/vi/ff4ofql6kX8/hqdefault.jpg",
                    "width": 480,
                    "height": 360
                },
                "standard": {
                    "url": "https://i.ytimg.com/vi/ff4ofql6kX8/sddefault.jpg",
                    "width": 640,
                    "height": 480
                },
                "maxres": {
                    "url": "https://i.ytimg.com/vi/ff4ofql6kX8/maxresdefault.jpg",
                    "width": 1280,
                    "height": 720
                }
            },
            "channelTitle": "Сама Меньшова",
            "tags": [
                "маяковский",
                "владимир маяковский",
                "меньшова",
                "сама меньшова",
                "меньшова маяковский",
                "маяковский лиля брик",
                "биография",
                "маяковский биография",
                "история жизни",
                "лиля брик",
                "владимир маяковский биография",
                "маяковский и лиля брик",
                "история любви",
                "маяковский володя лиля ося",
                "маяковский 1 серия",
                "маяковский брики",
                "юлия меньшова",
                "литература",
                "интересные факты"
            ],
            "categoryId": "24",
            "liveBroadcastContent": "none",
            "defaultLanguage": "ru",
            "localized": {
                "title": "\"Гений, Циник, Роковая женщина. В начале была игра\". МАЯКОВСКИЙ-БРИКИ. 1 серия @samamenshova",
                "description": "🎥Все серии МАЯКОВСКИЙ-БРИКИ https://www.youtube.com/playlist?list=PLLY5OYVYOkFbznJ15Jr6kKwABbgpL8jwb\n🎵 Альбом треков из сериала «Пожар сердца» https://zvonko.link/2077152\nИсполнитель — WWM// Маяк. Треки созданы полностью с помощью ИИ.\n\n«При вас этого бы не случилось!» — сказала мать Маяковского у гроба сына, обнимая Лилю и Осипа Брик, срочно вернувшихся из Берлина в Москву на похороны поэта. Неожиданно, правда? Кажется, современники, да и родные поэта, несколько иначе относились к этому знаменитому тройственному союзу, который сегодня принято исключительно клеймить. Так давайте вернемся к началу. Насколько справедливы ярлыки, приклеенные нами спустя 100 лет к его участникам? Лиля Брик — корыстная извращенка? Осип Брик — безвольный циник? Владимир Маяковский — доверчивый романтик?\nЖертвой коварной обольстительницы молодой поэт точно не был. Юный красавец и сам был горазд обольщать барышень из приличных семей, а потом бросать их, что с успехом проделал и в этот раз. Влюбившись в Лилю, он немедленно разорвал отношения с её родной сестрой Эльзой, хотя уже считался чуть ли не её женихом. Впрочем, сама Лиля к Маяковскому особого интереса не проявила, несмотря на потрясение его поэтическим талантом. Хотя она и заслужила репутацию femme fatale с ранних лет — её невероятное обаяние и манкость констатировали даже женщины, а мужчины и впрямь сходили с ума, — по иронии судьбы сама она всю жизнь смертельно любила лишь одного человека — собственного мужа. Но эта любовь не была взаимной…\nТайны и реальные подробности жизни самого скандального любовного треугольника XX века смотрите в нашем проекте «Маяковский — Брики. Володя. Лиля. Ося».\n\nСоцсети Юлии Меньшовой\nТелеграм: https://t.me/JuliaMenshovaJulia\nСообщество VK: https://vk.com/samamenshova\nRutube https://rutube.ru/u/samamenshova/\nЯндекс. Дзен: https://dzen.ru/samamenshova\nИнстаграм*: https://instagram.com/juliavmenshova\n\n#маяковский #брик #меньшова\n\n\n*Instagram — принадлежит американской компании Meta, которую признали экстремистской, запрещён на территории РФ."
            },
            "defaultAudioLanguage": "ru"
        },
        "contentDetails": {
            "duration": "PT28M15S",
            "dimension": "2d",
            "definition": "hd",
            "caption": "false",
            "licensedContent": true,
            "contentRating": {},
            "projection": "rectangular"
        },
        "statistics": {
            "viewCount": "472716",
            "likeCount": "17067",
            "favoriteCount": "0",
            "commentCount": "1163"
        }
    },
    {
        "kind": "youtube#video",
        "etag": "1eLvSDBeVqWxcefmLH6fAnrrh-0",
        "id": "2XkyblelVB0",
        "snippet": {
            "publishedAt": "2025-11-26T11:00:05Z",
            "channelId": "UCKyNmWAGzC-qhRxKg89Y9lg",
            "title": "\"Любляндия\": как сложился скандальный любовный треугольник? МАЯКОВСКИЙ-БРИКИ. 2 серия",
            "description": "🎥Все серии МАЯКОВСКИЙ-БРИКИ https://www.youtube.com/playlist?list=PLLY5OYVYOkFbznJ15Jr6kKwABbgpL8jwb\n🎵 Альбом треков из сериала «Пожар сердца» https://zvonko.link/2077152\nИсполнитель — WWM// Маяк. Треки созданы полностью с помощью ИИ.\n\nКогда вы слышите «брак втроём» — какие картинки возникают в вашей фантазии? Уверена, что все они будут весьма далеки от реальности отношений четы Брик и Владимира Маяковского. \nВо 2-й серии нашего сторителлинг-сериала вы узнаете, как именно сложился самый скандальный любовный треугольник ХХ века, и услышите немало шокирующих фактов и признаний. Например, одно из них принадлежит Лиле Брик: «если бы не Ося, я любила бы Володю не так сильно». Неожиданно, правда?\n\nПоявление 23-летнего футуриста Владимира Маяковского — дерзкого и необузданного — пробуждает небывалый пожар чувств в, казалось бы, циничном и невероятно эрудированном муже женщины, которую он назначил любовью всей своей жизни. В итоге Брик станет наставником поэта, продюсером и вдохновителем легендарного ЛЕФа, а поэт никогда не будет ревновать Осипа к его законной жене… Впрочем, это будет чуть позже. А пока Лиля превращает Маяковского из «нахала в дурацкой жёлтой кофте» в икону стиля с голливудской улыбкой и чеканной речью.\n\nНо за ширмой богемных петроградских вечеров скрывается мучительная драма. Лиля, обладательница дара с первого взгляда влюблять в себя любого, по-прежнему обречена на влечение к тому, кто её никогда не полюбит, а Маяковский, мечущийся в поисках утешения, пишет щемящие строки «Лилечки», в минуты слабости обращается к бывшим возлюбленным, срывается в Москву.\n\nСоцсети Юлии Меньшовой\nТелеграм: https://t.me/JuliaMenshovaJulia\nСообщество VK: https://vk.com/samamenshova\nRutube https://rutube.ru/u/samamenshova/\nЯндекс. Дзен: https://dzen.ru/samamenshova\nИнстаграм*: https://instagram.com/juliavmenshova\n\n#маяковский #брик #меньшова\n\n\n*Instagram — принадлежит американской компании Meta, которую признали экстремистской, запрещён на территории РФ.",
            "thumbnails": {
                "default": {
                    "url": "https://i.ytimg.com/vi/2XkyblelVB0/default.jpg",
                    "width": 120,
                    "height": 90
                },
                "medium": {
                    "url": "https://i.ytimg.com/vi/2XkyblelVB0/mqdefault.jpg",
                    "width": 320,
                    "height": 180
                },
                "high": {
                    "url": "https://i.ytimg.com/vi/2XkyblelVB0/hqdefault.jpg",
                    "width": 480,
                    "height": 360
                },
                "standard": {
                    "url": "https://i.ytimg.com/vi/2XkyblelVB0/sddefault.jpg",
                    "width": 640,
                    "height": 480
                },
                "maxres": {
                    "url": "https://i.ytimg.com/vi/2XkyblelVB0/maxresdefault.jpg",
                    "width": 1280,
                    "height": 720
                }
            },
            "channelTitle": "Сама Меньшова",
            "tags": [
                "маяковский",
                "владимир маяковский",
                "меньшова",
                "сама меньшова",
                "маяковский лиля брик",
                "биография",
                "маяковский биография",
                "история жизни",
                "лиля брик",
                "владимир маяковский биография",
                "маяковский и лиля брик",
                "история любви",
                "маяковский володя лиля ося",
                "маяковский 1 серия",
                "маяковский брики",
                "юлия меньшова",
                "литература",
                "интересные факты",
                "обучение",
                "маяковский меньшова",
                "маяковский сериал"
            ],
            "categoryId": "24",
            "liveBroadcastContent": "none",
            "defaultLanguage": "ru",
            "localized": {
                "title": "\"Любляндия\": как сложился скандальный любовный треугольник? МАЯКОВСКИЙ-БРИКИ. 2 серия",
                "description": "🎥Все серии МАЯКОВСКИЙ-БРИКИ https://www.youtube.com/playlist?list=PLLY5OYVYOkFbznJ15Jr6kKwABbgpL8jwb\n🎵 Альбом треков из сериала «Пожар сердца» https://zvonko.link/2077152\nИсполнитель — WWM// Маяк. Треки созданы полностью с помощью ИИ.\n\nКогда вы слышите «брак втроём» — какие картинки возникают в вашей фантазии? Уверена, что все они будут весьма далеки от реальности отношений четы Брик и Владимира Маяковского. \nВо 2-й серии нашего сторителлинг-сериала вы узнаете, как именно сложился самый скандальный любовный треугольник ХХ века, и услышите немало шокирующих фактов и признаний. Например, одно из них принадлежит Лиле Брик: «если бы не Ося, я любила бы Володю не так сильно». Неожиданно, правда?\n\nПоявление 23-летнего футуриста Владимира Маяковского — дерзкого и необузданного — пробуждает небывалый пожар чувств в, казалось бы, циничном и невероятно эрудированном муже женщины, которую он назначил любовью всей своей жизни. В итоге Брик станет наставником поэта, продюсером и вдохновителем легендарного ЛЕФа, а поэт никогда не будет ревновать Осипа к его законной жене… Впрочем, это будет чуть позже. А пока Лиля превращает Маяковского из «нахала в дурацкой жёлтой кофте» в икону стиля с голливудской улыбкой и чеканной речью.\n\nНо за ширмой богемных петроградских вечеров скрывается мучительная драма. Лиля, обладательница дара с первого взгляда влюблять в себя любого, по-прежнему обречена на влечение к тому, кто её никогда не полюбит, а Маяковский, мечущийся в поисках утешения, пишет щемящие строки «Лилечки», в минуты слабости обращается к бывшим возлюбленным, срывается в Москву.\n\nСоцсети Юлии Меньшовой\nТелеграм: https://t.me/JuliaMenshovaJulia\nСообщество VK: https://vk.com/samamenshova\nRutube https://rutube.ru/u/samamenshova/\nЯндекс. Дзен: https://dzen.ru/samamenshova\nИнстаграм*: https://instagram.com/juliavmenshova\n\n#маяковский #брик #меньшова\n\n\n*Instagram — принадлежит американской компании Meta, которую признали экстремистской, запрещён на территории РФ."
            },
            "defaultAudioLanguage": "ru"
        },
        "contentDetails": {
            "duration": "PT26M36S",
            "dimension": "2d",
            "definition": "hd",
            "caption": "false",
            "licensedContent": true,
            "contentRating": {},
            "projection": "rectangular"
        },
        "statistics": {
            "viewCount": "272208",
            "likeCount": "11294",
            "favoriteCount": "0",
            "commentCount": "807"
        }
    },
    {
        "kind": "youtube#video",
        "etag": "geQFwR8c2AIH_6ycI-DaqOlTX0Y",
        "id": "zMcvySwde7g",
        "snippet": {
            "publishedAt": "2025-11-29T09:01:39Z",
            "channelId": "UCKyNmWAGzC-qhRxKg89Y9lg",
            "title": "\"Ревность - постыдный инстинкт. Крах любви втроём\". МАЯКОВСКИЙ-БРИКИ. 3 серия",
            "description": "🎥Все серии МАЯКОВСКИЙ-БРИКИ https://www.youtube.com/playlist?list=PLLY5OYVYOkFbznJ15Jr6kKwABbgpL8jwb\n\n🎵 Альбом треков из сериала «Пожар сердца» https://zvonko.link/2077152\nИсполнитель — WWM// Маяк. Треки созданы полностью с помощью ИИ.\n\nМаниакальная страсть к чистоте, панический ужас перед любой заразой, отвращение к быту и... страх стать \"мужем и отцом\" — так, похоже, выразилась травма Владимира Маяковского после трагической смерти его отца. Женщин, которые могли бы составить конкуренцию Лиле Брик, в жизни поэта было немало, но их Маяковский, как точно заметит Осип Брик, всего лишь \"принимал к сведению\", а от любого большого чувства и вовсе бежал.\nОднако сколько бы ни провозглашали его современники ревность мещанством, и как бы ни зачитывал до дыр сам Маяковский любимую книжку всего этого поколения — «Что делать?» Чернышевского, истребить в себе собственнический инстинкт поэт так и не смог. Первая совместная зарубежная поездка Оси, Лили и Володи едва не закончилась полным разрывом отношений внутри любовного треугольника.\nНо отчаянная записка поэта, намекающая на потенциальное самоубийство, стала аргументом — расстаться лишь на пару месяцев.\nВо время этого \"отлучения\" Лиля начинает тайные отношения, которые заставляют её задумываться  о разрыве не только с Маяковским, но даже и с Осипом.\n\nСоцсети Юлии Меньшовой\nТелеграм: https://t.me/JuliaMenshovaJulia\nСообщество VK: https://vk.com/samamenshova\nRutube https://rutube.ru/u/samamenshova/\nЯндекс. Дзен: https://dzen.ru/samamenshova\nИнстаграм*: https://instagram.com/juliavmenshova\n\n#маяковский #брик #меньшова\n\n\n*Instagram — принадлежит американской компании Meta, которую признали экстремистской, запрещён на территории РФ.",
            "thumbnails": {
                "default": {
                    "url": "https://i.ytimg.com/vi/zMcvySwde7g/default.jpg",
                    "width": 120,
                    "height": 90
                },
                "medium": {
                    "url": "https://i.ytimg.com/vi/zMcvySwde7g/mqdefault.jpg",
                    "width": 320,
                    "height": 180
                },
                "high": {
                    "url": "https://i.ytimg.com/vi/zMcvySwde7g/hqdefault.jpg",
                    "width": 480,
                    "height": 360
                },
                "standard": {
                    "url": "https://i.ytimg.com/vi/zMcvySwde7g/sddefault.jpg",
                    "width": 640,
                    "height": 480
                },
                "maxres": {
                    "url": "https://i.ytimg.com/vi/zMcvySwde7g/maxresdefault.jpg",
                    "width": 1280,
                    "height": 720
                }
            },
            "channelTitle": "Сама Меньшова",
            "tags": [
                "маяковский",
                "владимир маяковский",
                "меньшова",
                "сама меньшова",
                "маяковский лиля брик",
                "биография",
                "маяковский биография",
                "история жизни",
                "лиля брик",
                "владимир маяковский биография",
                "маяковский и лиля брик",
                "история любви",
                "маяковский володя лиля ося",
                "маяковский 1 серия",
                "маяковский брики",
                "юлия меньшова",
                "литература",
                "интересные факты",
                "обучение",
                "маяковский меньшова",
                "маяковский сериал"
            ],
            "categoryId": "24",
            "liveBroadcastContent": "none",
            "defaultLanguage": "ru",
            "localized": {
                "title": "\"Ревность - постыдный инстинкт. Крах любви втроём\". МАЯКОВСКИЙ-БРИКИ. 3 серия",
                "description": "🎥Все серии МАЯКОВСКИЙ-БРИКИ https://www.youtube.com/playlist?list=PLLY5OYVYOkFbznJ15Jr6kKwABbgpL8jwb\n\n🎵 Альбом треков из сериала «Пожар сердца» https://zvonko.link/2077152\nИсполнитель — WWM// Маяк. Треки созданы полностью с помощью ИИ.\n\nМаниакальная страсть к чистоте, панический ужас перед любой заразой, отвращение к быту и... страх стать \"мужем и отцом\" — так, похоже, выразилась травма Владимира Маяковского после трагической смерти его отца. Женщин, которые могли бы составить конкуренцию Лиле Брик, в жизни поэта было немало, но их Маяковский, как точно заметит Осип Брик, всего лишь \"принимал к сведению\", а от любого большого чувства и вовсе бежал.\nОднако сколько бы ни провозглашали его современники ревность мещанством, и как бы ни зачитывал до дыр сам Маяковский любимую книжку всего этого поколения — «Что делать?» Чернышевского, истребить в себе собственнический инстинкт поэт так и не смог. Первая совместная зарубежная поездка Оси, Лили и Володи едва не закончилась полным разрывом отношений внутри любовного треугольника.\nНо отчаянная записка поэта, намекающая на потенциальное самоубийство, стала аргументом — расстаться лишь на пару месяцев.\nВо время этого \"отлучения\" Лиля начинает тайные отношения, которые заставляют её задумываться  о разрыве не только с Маяковским, но даже и с Осипом.\n\nСоцсети Юлии Меньшовой\nТелеграм: https://t.me/JuliaMenshovaJulia\nСообщество VK: https://vk.com/samamenshova\nRutube https://rutube.ru/u/samamenshova/\nЯндекс. Дзен: https://dzen.ru/samamenshova\nИнстаграм*: https://instagram.com/juliavmenshova\n\n#маяковский #брик #меньшова\n\n\n*Instagram — принадлежит американской компании Meta, которую признали экстремистской, запрещён на территории РФ."
            },
            "defaultAudioLanguage": "ru"
        },
        "contentDetails": {
            "duration": "PT28M29S",
            "dimension": "2d",
            "definition": "hd",
            "caption": "false",
            "licensedContent": true,
            "contentRating": {},
            "projection": "rectangular"
        },
        "statistics": {
            "viewCount": "246448",
            "likeCount": "9853",
            "favoriteCount": "0",
            "commentCount": "766"
        }
    },
    {
        "kind": "youtube#video",
        "etag": "zEMUb8F_VX-ljll8tKjo7bGhzvM",
        "id": "xqIuoFWxIho",
        "snippet": {
            "publishedAt": "2025-12-03T11:02:03Z",
            "channelId": "UCKyNmWAGzC-qhRxKg89Y9lg",
            "title": "\"Тайная дочь. Почему Маяковский скрывал её от Лили и Осипа ?\" МАЯКОВСКИЙ-БРИКИ. 4 серия",
            "description": "Чёрная полоса премиума прошла. Начинается белая — с Alfa Only. Подключите премиальный сервис Альфа-Банка до 15 января, а мы подарим 100 сертификатов по 100 тысяч рублей на культовые рестораны Москвы. https://alfa.me/4GAea0?erid=2W5zFGdHb5r\n\n🎥Все серии МАЯКОВСКИЙ-БРИКИ https://www.youtube.com/playlist?list=PLLY5OYVYOkFbznJ15Jr6kKwABbgpL8jwb\n🎵 Альбом треков из сериала «Пожар сердца» https://zvonko.link/2077152\nИсполнитель — WWM// Маяк. Треки созданы полностью с помощью ИИ.\n\nМосква, 1925 год.\nРядовая театральная премьера оборачивается грандиозным скандалом: в роковой любовнице, разорившей дотла героя пьесы «Воздушный пирог», вся столица узнает… Лилю Брик.\n\nИ это совсем не вымысел.\n«Тройственный союз», действительно, на грани распада. \nЛиля готова бросить своих ручных «звериков» — и Володю, и даже Осю! — ради деятельного главы советского Промбанка Александра Краснощёкова.\nНо Маяковский не подозревает об этом: запертый на «любовном карантине», он чуть ли не буквально сходит с ума в своем кабинете на Лубянке и пишет для Лили поэму «Про это».\n\nОкончательные перемены в их отношениях наступят лишь после поездки поэта в Америку.\nВ Нью-Йорке Маяковский встречает русскую эмигрантку Елизавету Зиберт, она же — Элли Джонс. \nВнешне она невероятно похожа  на Лилю, но  Элли понимает любовь совсем иначе — жертвенно и бескорыстно. \nЭто были два месяца странного, подпольного счастья поэта.\n\nВ 4 серии вы узнаете о том, как Маяковский нашел идеальную любовь и …отказался от неё.\nИ почему до конца жизни он хранил тайну рождения своей американской дочери. \nИ более всего оберегал этот секрет  от своих ближайших друзей, которых даже называл своей семьей, — Осипа и Лили Брик?\n\nСоцсети Юлии Меньшовой\nТелеграм: https://t.me/JuliaMenshovaJulia\nСообщество VK: https://vk.com/samamenshova\nRutube https://rutube.ru/u/samamenshova/\nЯндекс. Дзен: https://dzen.ru/samamenshova\nИнстаграм*: https://instagram.com/juliavmenshova\n\n#маяковский #брик #меньшова\n\nНезаконное потребление наркотических средств, психотропных веществ, их аналогов причиняет вред здоровью, их незаконный оборот запрещен и влечет установленную законодательством ответственность.\n\n*Instagram — принадлежит американской компании Meta, которую признали экстремистской, запрещён на территории РФ.",
            "thumbnails": {
                "default": {
                    "url": "https://i.ytimg.com/vi/xqIuoFWxIho/default.jpg",
                    "width": 120,
                    "height": 90
                },
                "medium": {
                    "url": "https://i.ytimg.com/vi/xqIuoFWxIho/mqdefault.jpg",
                    "width": 320,
                    "height": 180
                },
                "high": {
                    "url": "https://i.ytimg.com/vi/xqIuoFWxIho/hqdefault.jpg",
                    "width": 480,
                    "height": 360
                },
                "standard": {
                    "url": "https://i.ytimg.com/vi/xqIuoFWxIho/sddefault.jpg",
                    "width": 640,
                    "height": 480
                },
                "maxres": {
                    "url": "https://i.ytimg.com/vi/xqIuoFWxIho/maxresdefault.jpg",
                    "width": 1280,
                    "height": 720
                }
            },
            "channelTitle": "Сама Меньшова",
            "tags": [
                "маяковский",
                "владимир маяковский",
                "меньшова",
                "сама меньшова",
                "маяковский лиля брик",
                "биография",
                "маяковский биография",
                "история жизни",
                "лиля брик",
                "владимир маяковский биография",
                "маяковский и лиля брик",
                "история любви",
                "маяковский володя лиля ося",
                "маяковский 4 серия",
                "маяковский брики",
                "юлия меньшова",
                "литература",
                "интересные факты",
                "маяковский меньшова",
                "маяковский сериал",
                "лиля брик маяковский",
                "сама меньшова маяковский",
                "дочь маяковского",
                "поэт маяковский"
            ],
            "categoryId": "24",
            "liveBroadcastContent": "none",
            "defaultLanguage": "ru",
            "localized": {
                "title": "\"Тайная дочь. Почему Маяковский скрывал её от Лили и Осипа ?\" МАЯКОВСКИЙ-БРИКИ. 4 серия",
                "description": "Чёрная полоса премиума прошла. Начинается белая — с Alfa Only. Подключите премиальный сервис Альфа-Банка до 15 января, а мы подарим 100 сертификатов по 100 тысяч рублей на культовые рестораны Москвы. https://alfa.me/4GAea0?erid=2W5zFGdHb5r\n\n🎥Все серии МАЯКОВСКИЙ-БРИКИ https://www.youtube.com/playlist?list=PLLY5OYVYOkFbznJ15Jr6kKwABbgpL8jwb\n🎵 Альбом треков из сериала «Пожар сердца» https://zvonko.link/2077152\nИсполнитель — WWM// Маяк. Треки созданы полностью с помощью ИИ.\n\nМосква, 1925 год.\nРядовая театральная премьера оборачивается грандиозным скандалом: в роковой любовнице, разорившей дотла героя пьесы «Воздушный пирог», вся столица узнает… Лилю Брик.\n\nИ это совсем не вымысел.\n«Тройственный союз», действительно, на грани распада. \nЛиля готова бросить своих ручных «звериков» — и Володю, и даже Осю! — ради деятельного главы советского Промбанка Александра Краснощёкова.\nНо Маяковский не подозревает об этом: запертый на «любовном карантине», он чуть ли не буквально сходит с ума в своем кабинете на Лубянке и пишет для Лили поэму «Про это».\n\nОкончательные перемены в их отношениях наступят лишь после поездки поэта в Америку.\nВ Нью-Йорке Маяковский встречает русскую эмигрантку Елизавету Зиберт, она же — Элли Джонс. \nВнешне она невероятно похожа  на Лилю, но  Элли понимает любовь совсем иначе — жертвенно и бескорыстно. \nЭто были два месяца странного, подпольного счастья поэта.\n\nВ 4 серии вы узнаете о том, как Маяковский нашел идеальную любовь и …отказался от неё.\nИ почему до конца жизни он хранил тайну рождения своей американской дочери. \nИ более всего оберегал этот секрет  от своих ближайших друзей, которых даже называл своей семьей, — Осипа и Лили Брик?\n\nСоцсети Юлии Меньшовой\nТелеграм: https://t.me/JuliaMenshovaJulia\nСообщество VK: https://vk.com/samamenshova\nRutube https://rutube.ru/u/samamenshova/\nЯндекс. Дзен: https://dzen.ru/samamenshova\nИнстаграм*: https://instagram.com/juliavmenshova\n\n#маяковский #брик #меньшова\n\nНезаконное потребление наркотических средств, психотропных веществ, их аналогов причиняет вред здоровью, их незаконный оборот запрещен и влечет установленную законодательством ответственность.\n\n*Instagram — принадлежит американской компании Meta, которую признали экстремистской, запрещён на территории РФ."
            },
            "defaultAudioLanguage": "ru"
        },
        "contentDetails": {
            "duration": "PT29M54S",
            "dimension": "2d",
            "definition": "hd",
            "caption": "false",
            "licensedContent": true,
            "contentRating": {},
            "projection": "rectangular"
        },
        "statistics": {
            "viewCount": "224897",
            "likeCount": "9948",
            "favoriteCount": "0",
            "commentCount": "789"
        }
    },
    {
        "kind": "youtube#video",
        "etag": "b8R859yxW6fjaUxnMuvNBRe8vEc",
        "id": "TxS5gK1zbWc",
        "snippet": {
            "publishedAt": "2025-12-10T11:01:03Z",
            "channelId": "UCKyNmWAGzC-qhRxKg89Y9lg",
            "title": "Встреча Маяковского с дочкой, планы жениться и новая безумная любовь. БРИКИ-МАЯКОВСКИЙ. 5 серия",
            "description": "🎥Все серии МАЯКОВСКИЙ-БРИКИ https://www.youtube.com/playlist?list=PLLY5OYVYOkFbznJ15Jr6kKwABbgpL8jwb\n🎵 Альбом треков из сериала «Пожар сердца» https://zvonko.link/2077152\nИсполнитель — WWM// Маяк. Треки созданы полностью с помощью ИИ.\n\nМаяковский возвращается из Америки и получает ордер на новую квартиру. \nНа её дверях он вновь собственными руками крепит табличку «Брики. Маяковский».  \nЛиля, Ося и Володя съезжаются вместе, но счастливым, пожалуй, тут выглядит только Осип, неожиданно нашедший свою большую любовь. \nПоэт же чувствует себя в этом «общем доме» всё более одиноким и задумывает жениться.  Маяковский красиво ухаживает, церемонно пьет чай с семейством, скупает все цветы в ларьках или все духи Ялты для своих возлюбленных, но как только дело доходит до какой-либо определённости — не предпринимает никаких шагов. \nПо сути, сбегает из отношений, по-прежнему прикрываясь именем Лили как щитом.\n\nМеж тем, на другом континенте подрастает дочь поэта. Тайная встреча с ней и Элли  произойдёт в Ницце, почти случайно. Три дня они проведут вместе. Слёзы счастья и бесконечная  нежность... \nЭлли готова по первому же зову примчаться за Маяковским в Советскую Россию, но страстно призывать вернуться на родину поэт будет совсем другую женщину. \nТатьяну Яковлеву он встретит, едва покинув  Ниццу.  \nИ влюбится настолько, что не заметит реальности, которая, как кажется, вскоре и предопределит его трагический финал.\n\nСоцсети Юлии Меньшовой\nТелеграм: https://t.me/JuliaMenshovaJulia\nСообщество VK: https://vk.com/samamenshova\nRutube https://rutube.ru/u/samamenshova/\nЯндекс. Дзен: https://dzen.ru/samamenshova\nИнстаграм*: https://instagram.com/juliavmenshova\n\n#маяковский #брик #меньшова\n\n\n*Instagram — принадлежит американской компании Meta, которую признали экстремистской, запрещён на территории РФ.",
            "thumbnails": {
                "default": {
                    "url": "https://i.ytimg.com/vi/TxS5gK1zbWc/default.jpg",
                    "width": 120,
                    "height": 90
                },
                "medium": {
                    "url": "https://i.ytimg.com/vi/TxS5gK1zbWc/mqdefault.jpg",
                    "width": 320,
                    "height": 180
                },
                "high": {
                    "url": "https://i.ytimg.com/vi/TxS5gK1zbWc/hqdefault.jpg",
                    "width": 480,
                    "height": 360
                },
                "standard": {
                    "url": "https://i.ytimg.com/vi/TxS5gK1zbWc/sddefault.jpg",
                    "width": 640,
                    "height": 480
                },
                "maxres": {
                    "url": "https://i.ytimg.com/vi/TxS5gK1zbWc/maxresdefault.jpg",
                    "width": 1280,
                    "height": 720
                }
            },
            "channelTitle": "Сама Меньшова",
            "tags": [
                "маяковский",
                "владимир маяковский",
                "меньшова",
                "сама меньшова",
                "маяковский лиля брик",
                "биография",
                "маяковский биография",
                "история жизни",
                "лиля брик",
                "владимир маяковский биография",
                "маяковский и лиля брик",
                "история любви",
                "маяковский володя лиля ося",
                "маяковский брики",
                "юлия меньшова",
                "литература",
                "интересные факты",
                "маяковский меньшова",
                "маяковский сериал",
                "лиля брик маяковский",
                "сама меньшова маяковский",
                "поэт маяковский",
                "маяковский 5 серия"
            ],
            "categoryId": "24",
            "liveBroadcastContent": "none",
            "defaultLanguage": "ru",
            "localized": {
                "title": "Встреча Маяковского с дочкой, планы жениться и новая безумная любовь. БРИКИ-МАЯКОВСКИЙ. 5 серия",
                "description": "🎥Все серии МАЯКОВСКИЙ-БРИКИ https://www.youtube.com/playlist?list=PLLY5OYVYOkFbznJ15Jr6kKwABbgpL8jwb\n🎵 Альбом треков из сериала «Пожар сердца» https://zvonko.link/2077152\nИсполнитель — WWM// Маяк. Треки созданы полностью с помощью ИИ.\n\nМаяковский возвращается из Америки и получает ордер на новую квартиру. \nНа её дверях он вновь собственными руками крепит табличку «Брики. Маяковский».  \nЛиля, Ося и Володя съезжаются вместе, но счастливым, пожалуй, тут выглядит только Осип, неожиданно нашедший свою большую любовь. \nПоэт же чувствует себя в этом «общем доме» всё более одиноким и задумывает жениться.  Маяковский красиво ухаживает, церемонно пьет чай с семейством, скупает все цветы в ларьках или все духи Ялты для своих возлюбленных, но как только дело доходит до какой-либо определённости — не предпринимает никаких шагов. \nПо сути, сбегает из отношений, по-прежнему прикрываясь именем Лили как щитом.\n\nМеж тем, на другом континенте подрастает дочь поэта. Тайная встреча с ней и Элли  произойдёт в Ницце, почти случайно. Три дня они проведут вместе. Слёзы счастья и бесконечная  нежность... \nЭлли готова по первому же зову примчаться за Маяковским в Советскую Россию, но страстно призывать вернуться на родину поэт будет совсем другую женщину. \nТатьяну Яковлеву он встретит, едва покинув  Ниццу.  \nИ влюбится настолько, что не заметит реальности, которая, как кажется, вскоре и предопределит его трагический финал.\n\nСоцсети Юлии Меньшовой\nТелеграм: https://t.me/JuliaMenshovaJulia\nСообщество VK: https://vk.com/samamenshova\nRutube https://rutube.ru/u/samamenshova/\nЯндекс. Дзен: https://dzen.ru/samamenshova\nИнстаграм*: https://instagram.com/juliavmenshova\n\n#маяковский #брик #меньшова\n\n\n*Instagram — принадлежит американской компании Meta, которую признали экстремистской, запрещён на территории РФ."
            },
            "defaultAudioLanguage": "ru"
        },
        "contentDetails": {
            "duration": "PT27M48S",
            "dimension": "2d",
            "definition": "hd",
            "caption": "false",
            "licensedContent": true,
            "contentRating": {},
            "projection": "rectangular"
        },
        "statistics": {
            "viewCount": "203341",
            "likeCount": "9991",
            "favoriteCount": "0",
            "commentCount": "841"
        }
    },
    {
        "kind": "youtube#video",
        "etag": "8Gy2rgqHktJtFSRr0jqjKCw84GQ",
        "id": "7t2ZbidYisg",
        "snippet": {
            "publishedAt": "2025-12-17T11:00:23Z",
            "channelId": "UCKyNmWAGzC-qhRxKg89Y9lg",
            "title": "Роман с Татьяной Яковлевой — роковая ошибка поэта. МАЯКОВСКИЙ-БРИКИ. 6 серия @samamenshova",
            "description": "🎥Все серии МАЯКОВСКИЙ-БРИКИ https://www.youtube.com/playlist?list=PLLY5OYVYOkFbznJ15Jr6kKwABbgpL8jwb\n\n🎵 Альбом треков из сериала «Пожар сердца» https://zvonko.link/2077152\nИсполнитель — WWM// Маяк. Треки созданы полностью с помощью ИИ.\n\nМаяковский снова в Париже. Он знакомится с Татьяной Яковлевой — русской эмигранткой, манекенщицей самого дома Chanel, улыбающейся с рекламных плакатов по всему городу. Кроме того, юная красавица, как замечает Эльза Триоле, — единственная, кто «ростом вровень» великану советской поэзии. Татьяне чуть за двадцать, она окружена сотнями поклонников, но ведет себя неприступно.\nИдеальный набор обстоятельств, чтобы Маяковский настолько потерял голову, что вскоре даже готов к … обряду венчания.\n\nБолее того, поэт впервые посвящает свои стихи не Лиле Брик. Этот факт смертельно её обижает, она скажет: «Володя, ты впервые меня предал». Но Маяковский, собственно, и планирует расстаться. Похоже, в качестве красивой финальной точки в отношениях он привозит Лиле в подарок из Парижа автомобиль, о котором она так давно мечтала.\n\nОднако вполне скромный серый «Рено» взрывает советское общество. Личные автомобили в это время есть только у членов правительства. Что вообще себе позволяет этот пролетарский поэт? Опубликованные стихи о любви Маяковского к белоэмигрантке лишь подливают масла в полыхающий огонь. Маяковский впервые в жизни вынужден громко оправдываться, но по сути не замечает, что именно страстный роман с Яковлевой становится началом его конца…\n\nСоцсети Юлии Меньшовой\nТелеграм: https://t.me/JuliaMenshovaJulia\nСообщество VK: https://vk.com/samamenshova\nRutube https://rutube.ru/u/samamenshova/\nЯндекс. Дзен: https://dzen.ru/samamenshova\nИнстаграм*: https://instagram.com/juliavmenshova\n\n#маяковский #брик #меньшова\n\n\n*Instagram — принадлежит американской компании Meta, которую признали экстремистской, запрещён на территории РФ.",
            "thumbnails": {
                "default": {
                    "url": "https://i.ytimg.com/vi/7t2ZbidYisg/default.jpg",
                    "width": 120,
                    "height": 90
                },
                "medium": {
                    "url": "https://i.ytimg.com/vi/7t2ZbidYisg/mqdefault.jpg",
                    "width": 320,
                    "height": 180
                },
                "high": {
                    "url": "https://i.ytimg.com/vi/7t2ZbidYisg/hqdefault.jpg",
                    "width": 480,
                    "height": 360
                },
                "standard": {
                    "url": "https://i.ytimg.com/vi/7t2ZbidYisg/sddefault.jpg",
                    "width": 640,
                    "height": 480
                },
                "maxres": {
                    "url": "https://i.ytimg.com/vi/7t2ZbidYisg/maxresdefault.jpg",
                    "width": 1280,
                    "height": 720
                }
            },
            "channelTitle": "Сама Меньшова",
            "tags": [
                "маяковский",
                "владимир маяковский",
                "меньшова",
                "сама меньшова",
                "маяковский лиля брик",
                "биография",
                "маяковский биография",
                "история жизни",
                "лиля брик",
                "владимир маяковский биография",
                "маяковский и лиля брик",
                "история любви",
                "маяковский володя лиля ося",
                "маяковский брики",
                "юлия меньшова",
                "литература",
                "интересные факты",
                "маяковский меньшова",
                "маяковский сериал",
                "лиля брик маяковский",
                "сама меньшова маяковский",
                "поэт маяковский",
                "маяковский 6 серия"
            ],
            "categoryId": "24",
            "liveBroadcastContent": "none",
            "defaultLanguage": "ru",
            "localized": {
                "title": "Роман с Татьяной Яковлевой — роковая ошибка поэта. МАЯКОВСКИЙ-БРИКИ. 6 серия @samamenshova",
                "description": "🎥Все серии МАЯКОВСКИЙ-БРИКИ https://www.youtube.com/playlist?list=PLLY5OYVYOkFbznJ15Jr6kKwABbgpL8jwb\n\n🎵 Альбом треков из сериала «Пожар сердца» https://zvonko.link/2077152\nИсполнитель — WWM// Маяк. Треки созданы полностью с помощью ИИ.\n\nМаяковский снова в Париже. Он знакомится с Татьяной Яковлевой — русской эмигранткой, манекенщицей самого дома Chanel, улыбающейся с рекламных плакатов по всему городу. Кроме того, юная красавица, как замечает Эльза Триоле, — единственная, кто «ростом вровень» великану советской поэзии. Татьяне чуть за двадцать, она окружена сотнями поклонников, но ведет себя неприступно.\nИдеальный набор обстоятельств, чтобы Маяковский настолько потерял голову, что вскоре даже готов к … обряду венчания.\n\nБолее того, поэт впервые посвящает свои стихи не Лиле Брик. Этот факт смертельно её обижает, она скажет: «Володя, ты впервые меня предал». Но Маяковский, собственно, и планирует расстаться. Похоже, в качестве красивой финальной точки в отношениях он привозит Лиле в подарок из Парижа автомобиль, о котором она так давно мечтала.\n\nОднако вполне скромный серый «Рено» взрывает советское общество. Личные автомобили в это время есть только у членов правительства. Что вообще себе позволяет этот пролетарский поэт? Опубликованные стихи о любви Маяковского к белоэмигрантке лишь подливают масла в полыхающий огонь. Маяковский впервые в жизни вынужден громко оправдываться, но по сути не замечает, что именно страстный роман с Яковлевой становится началом его конца…\n\nСоцсети Юлии Меньшовой\nТелеграм: https://t.me/JuliaMenshovaJulia\nСообщество VK: https://vk.com/samamenshova\nRutube https://rutube.ru/u/samamenshova/\nЯндекс. Дзен: https://dzen.ru/samamenshova\nИнстаграм*: https://instagram.com/juliavmenshova\n\n#маяковский #брик #меньшова\n\n\n*Instagram — принадлежит американской компании Meta, которую признали экстремистской, запрещён на территории РФ."
            },
            "defaultAudioLanguage": "ru"
        },
        "contentDetails": {
            "duration": "PT21M46S",
            "dimension": "2d",
            "definition": "hd",
            "caption": "false",
            "licensedContent": true,
            "contentRating": {},
            "projection": "rectangular"
        },
        "statistics": {
            "viewCount": "163435",
            "likeCount": "8456",
            "favoriteCount": "0",
            "commentCount": "468"
        }
    },
    {
        "kind": "youtube#video",
        "etag": "iHLkysmJkPQUEBPuLphu7cbSVhI",
        "id": "MfO8Hh87fpc",
        "snippet": {
            "publishedAt": "2025-12-24T11:00:43Z",
            "channelId": "UCKyNmWAGzC-qhRxKg89Y9lg",
            "title": "Шпионские игры. Были ли поэт и супруги Брики агентами ОГПУ? МАЯКОВСКИЙ-БРИКИ. 7 серия",
            "description": "🎥Все серии МАЯКОВСКИЙ-БРИКИ https://www.youtube.com/playlist?list=PLLY5OYVYOkFbznJ15Jr6kKwABbgpL8jwb\n\n🎵 Альбом треков из сериала «Пожар сердца» https://zvonko.link/2077152\nИсполнитель — WWM// Маяк. Треки созданы полностью с помощью ИИ.\n\n1929 год. Маяковскому скоро исполнится 36, и он невероятно боится старости, панически реагирует на любые её признаки — лишний вес или новые морщинки.\nНо гораздо больше поэта пугает потеря голоса, который всегда был его главным оружием. Однако врачи выносят приговор: связки надорваны непоправимо.\n\nПытаясь убежать от накрывающей депрессии, поэт раньше назначенного срока срывается в Париж, к своей новой возлюбленной — Татьяне Яковлевой. Он мечтает о скорой свадьбе, но эта поездка оборачивается почти катастрофой.\n«Госиздат» впервые отказывается переводить ему гонорар в валюте за границу, и Маяковский остается совсем без гроша. В отчаянии поэт вместе с Татьяной едет в Монте-Карло, надеясь переиграть судьбу, но в итоге — проигрывает последние франки.\n\nНесчастный и раздавленный Маяковский рыдает в дешевом кафе перед своим давним приятелем-эмигрантом Анненковым. И даже вдруг признается, что давно уже перестал быть творцом и превратился… в чиновника.\nНо беспомощность и уязвимое положение поэта внезапно взламывают лед и покоряют сердце красавицы Татьяны Яковлевой.\nПоэт покидает Париж, условившись о точной дате свадьбы — октябрь 1929 года.\n\nОднако Маяковский больше никогда не пересечет границу СССР.\nДолгие годы мы «знали» печальный факт, что злое ОГПУ не выпустило поэта к его невесте. Но архивные документы открыли шокирующую правду: он сам даже не подавал заявления на выезд. Что его остановило?\n\nВ этой серии мы попытаемся понять, почему Брики и Маяковский с такой легкостью путешествовали по миру.\nБыл ли их гостеприимный дом филиалом Лубянки, а сами они — агентами спецслужб, для которых «свободный выезд» был всего лишь частью работы?\n\nСоцсети Юлии Меньшовой\nТелеграм: https://t.me/JuliaMenshovaJulia\nСообщество VK: https://vk.com/samamenshova\nRutube https://rutube.ru/u/samamenshova/\nЯндекс. Дзен: https://dzen.ru/samamenshova\nИнстаграм*: https://instagram.com/juliavmenshova\n\n#маяковский #брик #меньшова\n\n\n*Instagram — принадлежит американской компании Meta, которую признали экстремистской, запрещён на территории РФ.",
            "thumbnails": {
                "default": {
                    "url": "https://i.ytimg.com/vi/MfO8Hh87fpc/default.jpg",
                    "width": 120,
                    "height": 90
                },
                "medium": {
                    "url": "https://i.ytimg.com/vi/MfO8Hh87fpc/mqdefault.jpg",
                    "width": 320,
                    "height": 180
                },
                "high": {
                    "url": "https://i.ytimg.com/vi/MfO8Hh87fpc/hqdefault.jpg",
                    "width": 480,
                    "height": 360
                },
                "standard": {
                    "url": "https://i.ytimg.com/vi/MfO8Hh87fpc/sddefault.jpg",
                    "width": 640,
                    "height": 480
                },
                "maxres": {
                    "url": "https://i.ytimg.com/vi/MfO8Hh87fpc/maxresdefault.jpg",
                    "width": 1280,
                    "height": 720
                }
            },
            "channelTitle": "Сама Меньшова",
            "tags": [
                "маяковский",
                "владимир маяковский",
                "меньшова",
                "сама меньшова",
                "маяковский лиля брик",
                "биография",
                "маяковский биография",
                "история жизни",
                "лиля брик",
                "владимир маяковский биография",
                "маяковский и лиля брик",
                "история любви",
                "маяковский володя лиля ося",
                "маяковский брики",
                "юлия меньшова",
                "литература",
                "интересные факты",
                "маяковский меньшова",
                "маяковский сериал",
                "лиля брик маяковский",
                "сама меньшова маяковский",
                "поэт маяковский",
                "маяковский 7 серия",
                "огпу"
            ],
            "categoryId": "24",
            "liveBroadcastContent": "none",
            "defaultLanguage": "ru",
            "localized": {
                "title": "Шпионские игры. Были ли поэт и супруги Брики агентами ОГПУ? МАЯКОВСКИЙ-БРИКИ. 7 серия",
                "description": "🎥Все серии МАЯКОВСКИЙ-БРИКИ https://www.youtube.com/playlist?list=PLLY5OYVYOkFbznJ15Jr6kKwABbgpL8jwb\n\n🎵 Альбом треков из сериала «Пожар сердца» https://zvonko.link/2077152\nИсполнитель — WWM// Маяк. Треки созданы полностью с помощью ИИ.\n\n1929 год. Маяковскому скоро исполнится 36, и он невероятно боится старости, панически реагирует на любые её признаки — лишний вес или новые морщинки.\nНо гораздо больше поэта пугает потеря голоса, который всегда был его главным оружием. Однако врачи выносят приговор: связки надорваны непоправимо.\n\nПытаясь убежать от накрывающей депрессии, поэт раньше назначенного срока срывается в Париж, к своей новой возлюбленной — Татьяне Яковлевой. Он мечтает о скорой свадьбе, но эта поездка оборачивается почти катастрофой.\n«Госиздат» впервые отказывается переводить ему гонорар в валюте за границу, и Маяковский остается совсем без гроша. В отчаянии поэт вместе с Татьяной едет в Монте-Карло, надеясь переиграть судьбу, но в итоге — проигрывает последние франки.\n\nНесчастный и раздавленный Маяковский рыдает в дешевом кафе перед своим давним приятелем-эмигрантом Анненковым. И даже вдруг признается, что давно уже перестал быть творцом и превратился… в чиновника.\nНо беспомощность и уязвимое положение поэта внезапно взламывают лед и покоряют сердце красавицы Татьяны Яковлевой.\nПоэт покидает Париж, условившись о точной дате свадьбы — октябрь 1929 года.\n\nОднако Маяковский больше никогда не пересечет границу СССР.\nДолгие годы мы «знали» печальный факт, что злое ОГПУ не выпустило поэта к его невесте. Но архивные документы открыли шокирующую правду: он сам даже не подавал заявления на выезд. Что его остановило?\n\nВ этой серии мы попытаемся понять, почему Брики и Маяковский с такой легкостью путешествовали по миру.\nБыл ли их гостеприимный дом филиалом Лубянки, а сами они — агентами спецслужб, для которых «свободный выезд» был всего лишь частью работы?\n\nСоцсети Юлии Меньшовой\nТелеграм: https://t.me/JuliaMenshovaJulia\nСообщество VK: https://vk.com/samamenshova\nRutube https://rutube.ru/u/samamenshova/\nЯндекс. Дзен: https://dzen.ru/samamenshova\nИнстаграм*: https://instagram.com/juliavmenshova\n\n#маяковский #брик #меньшова\n\n\n*Instagram — принадлежит американской компании Meta, которую признали экстремистской, запрещён на территории РФ."
            },
            "defaultAudioLanguage": "ru"
        },
        "contentDetails": {
            "duration": "PT25M7S",
            "dimension": "2d",
            "definition": "hd",
            "caption": "false",
            "licensedContent": true,
            "contentRating": {},
            "projection": "rectangular"
        },
        "statistics": {
            "viewCount": "169082",
            "likeCount": "8113",
            "favoriteCount": "0",
            "commentCount": "643"
        }
    },
    {
        "kind": "youtube#video",
        "etag": "Fvli9FoZo-q83teeVkK2ZPlmJCQ",
        "id": "d8WHh8Z1PMk",
        "snippet": {
            "publishedAt": "2026-01-03T09:00:55Z",
            "channelId": "UCKyNmWAGzC-qhRxKg89Y9lg",
            "title": "Советские миллионеры? Агент Лиля Брик и другие тайны тройственного союза. МАЯКОВСКИЙ-БРИКИ. 8 серия",
            "description": "🎥Все серии МАЯКОВСКИЙ-БРИКИ https://www.youtube.com/playlist?list=PLLY5OYVYOkFbznJ15Jr6kKwABbgpL8jwb\n\n🎵 Альбом треков из сериала «Пожар сердца» https://zvonko.link/2077152\nИсполнитель — WWM// Маяк. Треки созданы полностью с помощью ИИ.\n\nПока Москва в 20-е переживала тяжелейший кризис, голод и разруху, быт Маяковского и четы Бриков складывался на удивление благополучно. Лиля даже нанимает домработницу для частого приёма гостей.\nВозможно, секрет столь поразительного бытового комфорта заключался в новом месте работы Осипа Брика?\nОн поступает на службу в ЧК.\nИ с этого момента линия жизни «тройственного союза» становится весьма извилистой, наполняясь загадками, достойными детектива.\nКем на самом деле был Осип Брик на Лубянке: скромным юристом, выдающимся лингвистом или уполномоченным секретного иностранного отдела, выполнявшим особые поручения?\nИ какая роль в этой шпионской игре отводилась Лиле, чье удостоверение сотрудника ГПУ под номером 15073 будет найдено в закрытых архивах?\nВ этой серии мы обсудим версии, почему Маяковский и Брики настолько свободно выезжают в Париж и Берлин и живут там на широкую ногу в то время, когда для обычных советских граждан границы были на замке.\nИ попробуем разгадать финансовую тайну семьи: откуда брались валюта для путешествий и огромные суммы для азартных игр?\nБыл ли поэт просто «лицом» советской культуры на Западе или также участником большой разведывательной игры?\nИ почему в 1929 году Маяковский вдруг испытал смертельный страх?\n\nСоцсети Юлии Меньшовой\nТелеграм: https://t.me/JuliaMenshovaJulia\nСообщество VK: https://vk.com/samamenshova\nRutube https://rutube.ru/u/samamenshova/\nЯндекс. Дзен: https://dzen.ru/samamenshova\nИнстаграм*: https://instagram.com/juliavmenshova\n\n#маяковский #брик #меньшова\n\n\n*Instagram — принадлежит американской компании Meta, которую признали экстремистской, запрещён на территории РФ.",
            "thumbnails": {
                "default": {
                    "url": "https://i.ytimg.com/vi/d8WHh8Z1PMk/default.jpg",
                    "width": 120,
                    "height": 90
                },
                "medium": {
                    "url": "https://i.ytimg.com/vi/d8WHh8Z1PMk/mqdefault.jpg",
                    "width": 320,
                    "height": 180
                },
                "high": {
                    "url": "https://i.ytimg.com/vi/d8WHh8Z1PMk/hqdefault.jpg",
                    "width": 480,
                    "height": 360
                },
                "standard": {
                    "url": "https://i.ytimg.com/vi/d8WHh8Z1PMk/sddefault.jpg",
                    "width": 640,
                    "height": 480
                },
                "maxres": {
                    "url": "https://i.ytimg.com/vi/d8WHh8Z1PMk/maxresdefault.jpg",
                    "width": 1280,
                    "height": 720
                }
            },
            "channelTitle": "Сама Меньшова",
            "tags": [
                "маяковский",
                "владимир маяковский",
                "меньшова",
                "сама меньшова",
                "маяковский лиля брик",
                "биография",
                "маяковский биография",
                "история жизни",
                "лиля брик",
                "владимир маяковский биография",
                "маяковский и лиля брик",
                "история любви",
                "маяковский володя лиля ося",
                "маяковский брики",
                "юлия меньшова",
                "литература",
                "интересные факты",
                "маяковский меньшова",
                "маяковский сериал",
                "лиля брик маяковский",
                "сама меньшова маяковский",
                "поэт маяковский",
                "маяковский серия 8"
            ],
            "categoryId": "24",
            "liveBroadcastContent": "none",
            "defaultLanguage": "ru",
            "localized": {
                "title": "Советские миллионеры? Агент Лиля Брик и другие тайны тройственного союза. МАЯКОВСКИЙ-БРИКИ. 8 серия",
                "description": "🎥Все серии МАЯКОВСКИЙ-БРИКИ https://www.youtube.com/playlist?list=PLLY5OYVYOkFbznJ15Jr6kKwABbgpL8jwb\n\n🎵 Альбом треков из сериала «Пожар сердца» https://zvonko.link/2077152\nИсполнитель — WWM// Маяк. Треки созданы полностью с помощью ИИ.\n\nПока Москва в 20-е переживала тяжелейший кризис, голод и разруху, быт Маяковского и четы Бриков складывался на удивление благополучно. Лиля даже нанимает домработницу для частого приёма гостей.\nВозможно, секрет столь поразительного бытового комфорта заключался в новом месте работы Осипа Брика?\nОн поступает на службу в ЧК.\nИ с этого момента линия жизни «тройственного союза» становится весьма извилистой, наполняясь загадками, достойными детектива.\nКем на самом деле был Осип Брик на Лубянке: скромным юристом, выдающимся лингвистом или уполномоченным секретного иностранного отдела, выполнявшим особые поручения?\nИ какая роль в этой шпионской игре отводилась Лиле, чье удостоверение сотрудника ГПУ под номером 15073 будет найдено в закрытых архивах?\nВ этой серии мы обсудим версии, почему Маяковский и Брики настолько свободно выезжают в Париж и Берлин и живут там на широкую ногу в то время, когда для обычных советских граждан границы были на замке.\nИ попробуем разгадать финансовую тайну семьи: откуда брались валюта для путешествий и огромные суммы для азартных игр?\nБыл ли поэт просто «лицом» советской культуры на Западе или также участником большой разведывательной игры?\nИ почему в 1929 году Маяковский вдруг испытал смертельный страх?\n\nСоцсети Юлии Меньшовой\nТелеграм: https://t.me/JuliaMenshovaJulia\nСообщество VK: https://vk.com/samamenshova\nRutube https://rutube.ru/u/samamenshova/\nЯндекс. Дзен: https://dzen.ru/samamenshova\nИнстаграм*: https://instagram.com/juliavmenshova\n\n#маяковский #брик #меньшова\n\n\n*Instagram — принадлежит американской компании Meta, которую признали экстремистской, запрещён на территории РФ."
            },
            "defaultAudioLanguage": "ru"
        },
        "contentDetails": {
            "duration": "PT22M31S",
            "dimension": "2d",
            "definition": "hd",
            "caption": "false",
            "licensedContent": true,
            "contentRating": {},
            "projection": "rectangular"
        },
        "statistics": {
            "viewCount": "169303",
            "likeCount": "7562",
            "favoriteCount": "0",
            "commentCount": "427"
        }
    },
    {
        "kind": "youtube#video",
        "etag": "0x-NqtMNb4xOSXws02DUMSklCtQ",
        "id": "dErkuqKERfo",
        "snippet": {
            "publishedAt": "2026-01-07T09:01:06Z",
            "channelId": "UCKyNmWAGzC-qhRxKg89Y9lg",
            "title": "Последняя любовь поэта. МАЯКОВСКИЙ-БРИКИ. 9 серия @samamenshova",
            "description": "🎥Все серии МАЯКОВСКИЙ-БРИКИ https://www.youtube.com/playlist?list=PLLY5OYVYOkFbznJ15Jr6kKwABbgpL8jwb\n\n🎵 Альбом треков из сериала «Пожар сердца» https://zvonko.link/2077152\nИсполнитель — WWM// Маяк. Треки созданы полностью с помощью ИИ.\n\nВесной 1929 года Маяковский возвращается в Москву, полный надежд на скорую свадьбу с парижской красавицей Татьяной Яковлевой, и почти сразу знакомится с юной актрисой МХАТа Вероникой Полонской.\n21-летняя Нора замужем, но разве это когда-нибудь останавливало Маяковского? Их роман развивается стремительно и тайно: пока муж Норы верит в дружбу и творческий союз, влюбленные чуть ли не ежедневно встречаются в кабинете поэта на Лубянке.\nПри этом Маяковский продолжает слать в Париж нежные письма Татьяне Яковлевой, обещая вот-вот приехать.\nНо Париж закрыт.\nШпионский скандал с побегом советского дипломата делает на время невыездными всех, кто хоть как-то был связан с органами ОГПУ.\nМаяковский оказывается в ловушке: он не может объяснить в письмах Татьяне истинных причин своей задержки, а в это время Яковлева получает информацию о романе поэта с Полонской.\nИ спустя недолгое время в Москве узнают о скорой свадьбе Татьяны с виконтом дю Плесси.\nЭто очередной удар для самолюбия Маяковского, он мрачнеет, но на вопрос Лили, не думает ли он покончить с собой, отвечает: «Эта лошадь кончилась, пересел на другую».\n\nСоцсети Юлии Меньшовой\nТелеграм: https://t.me/JuliaMenshovaJulia\nСообщество VK: https://vk.com/samamenshova\nRutube https://rutube.ru/u/samamenshova/\nЯндекс. Дзен: https://dzen.ru/samamenshova\nИнстаграм*: https://instagram.com/juliavmenshova\n\n#маяковский #брик #меньшова\n\n\n*Instagram — принадлежит американской компании Meta, которую признали экстремистской, запрещён на территории РФ.",
            "thumbnails": {
                "default": {
                    "url": "https://i.ytimg.com/vi/dErkuqKERfo/default.jpg",
                    "width": 120,
                    "height": 90
                },
                "medium": {
                    "url": "https://i.ytimg.com/vi/dErkuqKERfo/mqdefault.jpg",
                    "width": 320,
                    "height": 180
                },
                "high": {
                    "url": "https://i.ytimg.com/vi/dErkuqKERfo/hqdefault.jpg",
                    "width": 480,
                    "height": 360
                },
                "standard": {
                    "url": "https://i.ytimg.com/vi/dErkuqKERfo/sddefault.jpg",
                    "width": 640,
                    "height": 480
                },
                "maxres": {
                    "url": "https://i.ytimg.com/vi/dErkuqKERfo/maxresdefault.jpg",
                    "width": 1280,
                    "height": 720
                }
            },
            "channelTitle": "Сама Меньшова",
            "tags": [
                "маяковский",
                "владимир маяковский",
                "меньшова",
                "сама меньшова",
                "маяковский лиля брик",
                "биография",
                "маяковский биография",
                "история жизни",
                "владимир маяковский биография",
                "маяковский и лиля брик",
                "история любви",
                "маяковский володя лиля ося",
                "маяковский брики",
                "юлия меньшова",
                "литература",
                "интересные факты",
                "маяковский меньшова",
                "маяковский сериал",
                "сама меньшова маяковский",
                "поэт маяковский",
                "маяковский серия 9",
                "полонская",
                "яковлева",
                "татьяна яковлева",
                "вероника полонская",
                "любовь"
            ],
            "categoryId": "24",
            "liveBroadcastContent": "none",
            "defaultLanguage": "ru",
            "localized": {
                "title": "Последняя любовь поэта. МАЯКОВСКИЙ-БРИКИ. 9 серия @samamenshova",
                "description": "🎥Все серии МАЯКОВСКИЙ-БРИКИ https://www.youtube.com/playlist?list=PLLY5OYVYOkFbznJ15Jr6kKwABbgpL8jwb\n\n🎵 Альбом треков из сериала «Пожар сердца» https://zvonko.link/2077152\nИсполнитель — WWM// Маяк. Треки созданы полностью с помощью ИИ.\n\nВесной 1929 года Маяковский возвращается в Москву, полный надежд на скорую свадьбу с парижской красавицей Татьяной Яковлевой, и почти сразу знакомится с юной актрисой МХАТа Вероникой Полонской.\n21-летняя Нора замужем, но разве это когда-нибудь останавливало Маяковского? Их роман развивается стремительно и тайно: пока муж Норы верит в дружбу и творческий союз, влюбленные чуть ли не ежедневно встречаются в кабинете поэта на Лубянке.\nПри этом Маяковский продолжает слать в Париж нежные письма Татьяне Яковлевой, обещая вот-вот приехать.\nНо Париж закрыт.\nШпионский скандал с побегом советского дипломата делает на время невыездными всех, кто хоть как-то был связан с органами ОГПУ.\nМаяковский оказывается в ловушке: он не может объяснить в письмах Татьяне истинных причин своей задержки, а в это время Яковлева получает информацию о романе поэта с Полонской.\nИ спустя недолгое время в Москве узнают о скорой свадьбе Татьяны с виконтом дю Плесси.\nЭто очередной удар для самолюбия Маяковского, он мрачнеет, но на вопрос Лили, не думает ли он покончить с собой, отвечает: «Эта лошадь кончилась, пересел на другую».\n\nСоцсети Юлии Меньшовой\nТелеграм: https://t.me/JuliaMenshovaJulia\nСообщество VK: https://vk.com/samamenshova\nRutube https://rutube.ru/u/samamenshova/\nЯндекс. Дзен: https://dzen.ru/samamenshova\nИнстаграм*: https://instagram.com/juliavmenshova\n\n#маяковский #брик #меньшова\n\n\n*Instagram — принадлежит американской компании Meta, которую признали экстремистской, запрещён на территории РФ."
            },
            "defaultAudioLanguage": "ru"
        },
        "contentDetails": {
            "duration": "PT28M5S",
            "dimension": "2d",
            "definition": "hd",
            "caption": "false",
            "licensedContent": true,
            "contentRating": {},
            "projection": "rectangular"
        },
        "statistics": {
            "viewCount": "159682",
            "likeCount": "8244",
            "favoriteCount": "0",
            "commentCount": "483"
        }
    },
    {
        "kind": "youtube#video",
        "etag": "XLwxQb6PY0Qw2MIWFpb3Q9EUXEs",
        "id": "QlKIROSdADA",
        "snippet": {
            "publishedAt": "2026-01-10T09:00:43Z",
            "channelId": "UCKyNmWAGzC-qhRxKg89Y9lg",
            "title": "Последний Новый год, беременность любовницы и чистки в рядах ОГПУ. МАЯКОВСКИЙ-БРИКИ. 10 серия",
            "description": "Чёрная полоса премиума прошла. Начинается белая — с Alfa Only. Подключите премиальный сервис Альфа-Банка до 15 января, а мы подарим 100 сертификатов по 100 тысяч рублей на культовые рестораны Москвы. https://alfa.me/581qPv?erid=2W5zFJZpwR2\n\n🎥Все серии МАЯКОВСКИЙ-БРИКИ https://www.youtube.com/playlist?list=PLLY5OYVYOkFbznJ15Jr6kKwABbgpL8jwb\n\n🎵 Альбом треков из сериала «Пожар сердца» https://zvonko.link/2077152\nИсполнитель — WWM// Маяк. Треки созданы полностью с помощью ИИ.\n\nМаяковский пытается сбежать от депрессивных мыслей в новый роман с актрисой Вероникой Полонской.\nСо стороны всё выглядит как идиллия: катание на санках, сердечки на снегу и даже разговоры о свадьбе. Но в реальности поэт все чаще изводит Нору сценами ревности, требует уйти от мужа и бросить театр.\nКульминацией становится тайный аборт, который сильно надломил психологическое состояние самой актрисы.\n\nНо эта любовная драма — лишь фон для куда более страшных событий. В ЧК и партии идут беспрецедентные чистки.\nРасстрелян давний приятель Маяковского — легендарный Яков Блюмкин, да и многие другие друзья из ОГПУ оказываются под ударом. Новая пьеса «Баня», задуманная как триумф сатиры и иронии, неожиданно становится поводом для проработок поэта на собраниях Главреперткома. Маяковский чувствует: он больше не главный голос эпохи. Но что ещё страшнее — возможно, её новая потенциальная жертва.\n\nВ отчаянной попытке доказать свою нужность власти он организовывает выставку «20 лет работы». Но друзья из РЕФа не считают правильной персональную выставку поэта. Маяковский ссорится насмерть со всем своим ближайшим окружением и встречает свой последний Новый год, загнанный самыми черными мыслями.\n\nСоцсети Юлии Меньшовой\nТелеграм: https://t.me/JuliaMenshovaJulia\nСообщество VK: https://vk.com/samamenshova\nRutube https://rutube.ru/u/samamenshova/\nЯндекс. Дзен: https://dzen.ru/samamenshova\nИнстаграм*: https://instagram.com/juliavmenshova\n\n#маяковский #брик #меньшова\n\n\n*Instagram — принадлежит американской компании Meta, которую признали экстремистской, запрещён на территории РФ.",
            "thumbnails": {
                "default": {
                    "url": "https://i.ytimg.com/vi/QlKIROSdADA/default.jpg",
                    "width": 120,
                    "height": 90
                },
                "medium": {
                    "url": "https://i.ytimg.com/vi/QlKIROSdADA/mqdefault.jpg",
                    "width": 320,
                    "height": 180
                },
                "high": {
                    "url": "https://i.ytimg.com/vi/QlKIROSdADA/hqdefault.jpg",
                    "width": 480,
                    "height": 360
                },
                "standard": {
                    "url": "https://i.ytimg.com/vi/QlKIROSdADA/sddefault.jpg",
                    "width": 640,
                    "height": 480
                },
                "maxres": {
                    "url": "https://i.ytimg.com/vi/QlKIROSdADA/maxresdefault.jpg",
                    "width": 1280,
                    "height": 720
                }
            },
            "channelTitle": "Сама Меньшова",
            "tags": [
                "маяковский",
                "владимир маяковский",
                "меньшова",
                "сама меньшова",
                "маяковский лиля брик",
                "биография",
                "маяковский биография",
                "история жизни",
                "лиля брик",
                "владимир маяковский биография",
                "маяковский и лиля брик",
                "история любви",
                "маяковский володя лиля ося",
                "маяковский брики",
                "юлия меньшова",
                "литература",
                "интересные факты",
                "маяковский меньшова",
                "маяковский сериал",
                "лиля брик маяковский",
                "сама меньшова маяковский",
                "поэт маяковский",
                "маяковский 10 серия",
                "огпу"
            ],
            "categoryId": "24",
            "liveBroadcastContent": "none",
            "defaultLanguage": "ru",
            "localized": {
                "title": "Последний Новый год, беременность любовницы и чистки в рядах ОГПУ. МАЯКОВСКИЙ-БРИКИ. 10 серия",
                "description": "Чёрная полоса премиума прошла. Начинается белая — с Alfa Only. Подключите премиальный сервис Альфа-Банка до 15 января, а мы подарим 100 сертификатов по 100 тысяч рублей на культовые рестораны Москвы. https://alfa.me/581qPv?erid=2W5zFJZpwR2\n\n🎥Все серии МАЯКОВСКИЙ-БРИКИ https://www.youtube.com/playlist?list=PLLY5OYVYOkFbznJ15Jr6kKwABbgpL8jwb\n\n🎵 Альбом треков из сериала «Пожар сердца» https://zvonko.link/2077152\nИсполнитель — WWM// Маяк. Треки созданы полностью с помощью ИИ.\n\nМаяковский пытается сбежать от депрессивных мыслей в новый роман с актрисой Вероникой Полонской.\nСо стороны всё выглядит как идиллия: катание на санках, сердечки на снегу и даже разговоры о свадьбе. Но в реальности поэт все чаще изводит Нору сценами ревности, требует уйти от мужа и бросить театр.\nКульминацией становится тайный аборт, который сильно надломил психологическое состояние самой актрисы.\n\nНо эта любовная драма — лишь фон для куда более страшных событий. В ЧК и партии идут беспрецедентные чистки.\nРасстрелян давний приятель Маяковского — легендарный Яков Блюмкин, да и многие другие друзья из ОГПУ оказываются под ударом. Новая пьеса «Баня», задуманная как триумф сатиры и иронии, неожиданно становится поводом для проработок поэта на собраниях Главреперткома. Маяковский чувствует: он больше не главный голос эпохи. Но что ещё страшнее — возможно, её новая потенциальная жертва.\n\nВ отчаянной попытке доказать свою нужность власти он организовывает выставку «20 лет работы». Но друзья из РЕФа не считают правильной персональную выставку поэта. Маяковский ссорится насмерть со всем своим ближайшим окружением и встречает свой последний Новый год, загнанный самыми черными мыслями.\n\nСоцсети Юлии Меньшовой\nТелеграм: https://t.me/JuliaMenshovaJulia\nСообщество VK: https://vk.com/samamenshova\nRutube https://rutube.ru/u/samamenshova/\nЯндекс. Дзен: https://dzen.ru/samamenshova\nИнстаграм*: https://instagram.com/juliavmenshova\n\n#маяковский #брик #меньшова\n\n\n*Instagram — принадлежит американской компании Meta, которую признали экстремистской, запрещён на территории РФ."
            },
            "defaultAudioLanguage": "ru"
        },
        "contentDetails": {
            "duration": "PT28M36S",
            "dimension": "2d",
            "definition": "hd",
            "caption": "false",
            "licensedContent": true,
            "contentRating": {},
            "projection": "rectangular"
        },
        "statistics": {
            "viewCount": "174903",
            "likeCount": "8929",
            "favoriteCount": "0",
            "commentCount": "568"
        }
    },
    {
        "kind": "youtube#video",
        "etag": "DMWboWpuxR4a62Dkc8v_YTDiPUk",
        "id": "3rk-rt_wIOw",
        "snippet": {
            "publishedAt": "2026-01-14T11:00:06Z",
            "channelId": "UCKyNmWAGzC-qhRxKg89Y9lg",
            "title": "«Я тебя yбью» - ссора накануне рокового выстрела. МАЯКОВСКИЙ-БРИКИ. 11 серия @samamenshova",
            "description": "🎥Все серии МАЯКОВСКИЙ-БРИКИ https://www.youtube.com/playlist?list=PLLY5OYVYOkFbznJ15Jr6kKwABbgpL8jwb\n\n🎵 Альбом треков из сериала «Пожар сердца» https://zvonko.link/2077152\nИсполнитель — WWM// Маяк. Треки созданы полностью с помощью ИИ.\n\nВесна 1930 года превращается для Маяковского в затяжную агонию.\nПоэт маниакально сосредоточен на отношениях с Вероникой Полонской. Юная актриса сталкивается с тотальной слежкой и постоянными жестокими ультиматумами. Она измотана двойной жизнью и бесконечными скандалами, но не соглашается порвать с театром и уйти от мужа к человеку, чья психика явно расшатана до предела.\n\nЮбилейная выставка Маяковского «20 лет работы», на которую поэт сделал главную ставку в надежде доказать свою лояльность власти, оборачивается почти публичным унижением. На открытии зал полон молодежи, но те, кого Маяковский ждал на самом деле — партийная элита и значимые коллеги-писатели, — игнорируют разосланные приглашения. Поэту это кажется проявлением демонстративного бойкота. Он оказывается в социальном вакууме, и вступление поэта в ряды РАПП выглядит как капитуляция. Друзья в недоумении. Но и «враги» тоже.\n\nСцена, предвещающая страшную развязку, случается на вечеринке у Валентина Катаева. Пьяный и мрачный Маяковский устраивает публичный скандал Веронике Полонской. Когда они остаются наедине, поэт достает револьвер, то наводя дуло на себя, то на любимую женщину, угрожая убить её. Почти шантажом Маяковский выбивает из Норы обещание приехать в его кабинет на Лубянку следующим утром — 14 апреля 1930 года.\n\nСоцсети Юлии Меньшовой\nТелеграм: https://t.me/JuliaMenshovaJulia\nСообщество VK: https://vk.com/samamenshova\nRutube https://rutube.ru/u/samamenshova/\nЯндекс. Дзен: https://dzen.ru/samamenshova\nИнстаграм*: https://instagram.com/juliavmenshova\n\n#маяковский #брик #меньшова\n\n\n*Instagram — принадлежит американской компании Meta, которую признали экстремистской, запрещён на территории РФ.",
            "thumbnails": {
                "default": {
                    "url": "https://i.ytimg.com/vi/3rk-rt_wIOw/default.jpg",
                    "width": 120,
                    "height": 90
                },
                "medium": {
                    "url": "https://i.ytimg.com/vi/3rk-rt_wIOw/mqdefault.jpg",
                    "width": 320,
                    "height": 180
                },
                "high": {
                    "url": "https://i.ytimg.com/vi/3rk-rt_wIOw/hqdefault.jpg",
                    "width": 480,
                    "height": 360
                },
                "standard": {
                    "url": "https://i.ytimg.com/vi/3rk-rt_wIOw/sddefault.jpg",
                    "width": 640,
                    "height": 480
                },
                "maxres": {
                    "url": "https://i.ytimg.com/vi/3rk-rt_wIOw/maxresdefault.jpg",
                    "width": 1280,
                    "height": 720
                }
            },
            "channelTitle": "Сама Меньшова",
            "tags": [
                "маяковский",
                "владимир маяковский",
                "меньшова",
                "сама меньшова",
                "маяковский лиля брик",
                "биография",
                "маяковский биография",
                "история жизни",
                "лиля брик",
                "владимир маяковский биография",
                "маяковский и лиля брик",
                "история любви",
                "маяковский володя лиля ося",
                "маяковский брики",
                "юлия меньшова",
                "литература",
                "интересные факты",
                "маяковский меньшова",
                "маяковский сериал",
                "сама меньшова маяковский",
                "поэт маяковский",
                "маяковский 11 серия",
                "вероника полонская",
                "полонская"
            ],
            "categoryId": "24",
            "liveBroadcastContent": "none",
            "defaultLanguage": "ru",
            "localized": {
                "title": "«Я тебя yбью» - ссора накануне рокового выстрела. МАЯКОВСКИЙ-БРИКИ. 11 серия @samamenshova",
                "description": "🎥Все серии МАЯКОВСКИЙ-БРИКИ https://www.youtube.com/playlist?list=PLLY5OYVYOkFbznJ15Jr6kKwABbgpL8jwb\n\n🎵 Альбом треков из сериала «Пожар сердца» https://zvonko.link/2077152\nИсполнитель — WWM// Маяк. Треки созданы полностью с помощью ИИ.\n\nВесна 1930 года превращается для Маяковского в затяжную агонию.\nПоэт маниакально сосредоточен на отношениях с Вероникой Полонской. Юная актриса сталкивается с тотальной слежкой и постоянными жестокими ультиматумами. Она измотана двойной жизнью и бесконечными скандалами, но не соглашается порвать с театром и уйти от мужа к человеку, чья психика явно расшатана до предела.\n\nЮбилейная выставка Маяковского «20 лет работы», на которую поэт сделал главную ставку в надежде доказать свою лояльность власти, оборачивается почти публичным унижением. На открытии зал полон молодежи, но те, кого Маяковский ждал на самом деле — партийная элита и значимые коллеги-писатели, — игнорируют разосланные приглашения. Поэту это кажется проявлением демонстративного бойкота. Он оказывается в социальном вакууме, и вступление поэта в ряды РАПП выглядит как капитуляция. Друзья в недоумении. Но и «враги» тоже.\n\nСцена, предвещающая страшную развязку, случается на вечеринке у Валентина Катаева. Пьяный и мрачный Маяковский устраивает публичный скандал Веронике Полонской. Когда они остаются наедине, поэт достает револьвер, то наводя дуло на себя, то на любимую женщину, угрожая убить её. Почти шантажом Маяковский выбивает из Норы обещание приехать в его кабинет на Лубянку следующим утром — 14 апреля 1930 года.\n\nСоцсети Юлии Меньшовой\nТелеграм: https://t.me/JuliaMenshovaJulia\nСообщество VK: https://vk.com/samamenshova\nRutube https://rutube.ru/u/samamenshova/\nЯндекс. Дзен: https://dzen.ru/samamenshova\nИнстаграм*: https://instagram.com/juliavmenshova\n\n#маяковский #брик #меньшова\n\n\n*Instagram — принадлежит американской компании Meta, которую признали экстремистской, запрещён на территории РФ."
            },
            "defaultAudioLanguage": "ru"
        },
        "contentDetails": {
            "duration": "PT27M31S",
            "dimension": "2d",
            "definition": "hd",
            "caption": "false",
            "licensedContent": true,
            "contentRating": {},
            "projection": "rectangular"
        },
        "statistics": {
            "viewCount": "156901",
            "likeCount": "9386",
            "favoriteCount": "0",
            "commentCount": "670"
        }
    },
    {
        "kind": "youtube#video",
        "etag": "ytRn8tWi18BvTGs2bJZL35E70io",
        "id": "s1A1KtTEKo0",
        "snippet": {
            "publishedAt": "2026-01-17T09:01:25Z",
            "channelId": "UCKyNmWAGzC-qhRxKg89Y9lg",
            "title": "Последние часы поэта. Тайна кабинета на Лубянке. МАЯКОВСКИЙ-БРИКИ. 12 серия",
            "description": "🎥Все серии МАЯКОВСКИЙ-БРИКИ https://www.youtube.com/playlist?list=PLLY5OYVYOkFbznJ15Jr6kKwABbgpL8jwb\n🎵 Альбом треков из сериала «Пожар сердца» https://zvonko.link/2077152\nИсполнитель — WWM// Маяк. Треки созданы полностью с помощью ИИ.\n\n14 апреля 1930 года Лиля и Осип Брик находятся в Амстердаме.\nОни покупают подарки для Владимира Маяковского и отправляют ему тёплую телеграмму, не подозревая, что события в Москве уже приняли необратимый характер.\n\nВ небольшой комнате на Лубянке разворачивается последняя драма поэта. Напряжённый разговор с Норой Полонской становится кульминацией сложных отношений, внутренних конфликтов и эмоционального кризиса, который нарастал месяцами. И заканчивается трагедией. \n\nС этого дня жизнь Полонской резко изменится. Она оказывается в центре слухов, домыслов и обвинений, вынуждена давать объяснения для протокола.  \nПохороны Маяковского откладывают ради возвращения Осипа и Лили Брик из-за границы. \nНо их поведение вызывает множество разговоров и слухов, так же, как и их роль в жизни и наследии поэта.\n\nДолгие годы Осип и Лиля будут отстаивать имя Маяковского и бороться за его память, но его уход не стал концом их истории.\nСовсем скоро Лиля и Осип Брик вступят в новую шпионскую игру\n\n\nНезаконное потребление наркотических средств, психотропных веществ, их аналогов причиняет вред здоровью, их незаконный оборот запрещен и влечет установленную законодательством ответственность.",
            "thumbnails": {
                "default": {
                    "url": "https://i.ytimg.com/vi/s1A1KtTEKo0/default.jpg",
                    "width": 120,
                    "height": 90
                },
                "medium": {
                    "url": "https://i.ytimg.com/vi/s1A1KtTEKo0/mqdefault.jpg",
                    "width": 320,
                    "height": 180
                },
                "high": {
                    "url": "https://i.ytimg.com/vi/s1A1KtTEKo0/hqdefault.jpg",
                    "width": 480,
                    "height": 360
                },
                "standard": {
                    "url": "https://i.ytimg.com/vi/s1A1KtTEKo0/sddefault.jpg",
                    "width": 640,
                    "height": 480
                },
                "maxres": {
                    "url": "https://i.ytimg.com/vi/s1A1KtTEKo0/maxresdefault.jpg",
                    "width": 1280,
                    "height": 720
                }
            },
            "channelTitle": "Сама Меньшова",
            "categoryId": "24",
            "liveBroadcastContent": "none",
            "defaultLanguage": "ru",
            "localized": {
                "title": "Последние часы поэта. Тайна кабинета на Лубянке. МАЯКОВСКИЙ-БРИКИ. 12 серия",
                "description": "🎥Все серии МАЯКОВСКИЙ-БРИКИ https://www.youtube.com/playlist?list=PLLY5OYVYOkFbznJ15Jr6kKwABbgpL8jwb\n🎵 Альбом треков из сериала «Пожар сердца» https://zvonko.link/2077152\nИсполнитель — WWM// Маяк. Треки созданы полностью с помощью ИИ.\n\n14 апреля 1930 года Лиля и Осип Брик находятся в Амстердаме.\nОни покупают подарки для Владимира Маяковского и отправляют ему тёплую телеграмму, не подозревая, что события в Москве уже приняли необратимый характер.\n\nВ небольшой комнате на Лубянке разворачивается последняя драма поэта. Напряжённый разговор с Норой Полонской становится кульминацией сложных отношений, внутренних конфликтов и эмоционального кризиса, который нарастал месяцами. И заканчивается трагедией. \n\nС этого дня жизнь Полонской резко изменится. Она оказывается в центре слухов, домыслов и обвинений, вынуждена давать объяснения для протокола.  \nПохороны Маяковского откладывают ради возвращения Осипа и Лили Брик из-за границы. \nНо их поведение вызывает множество разговоров и слухов, так же, как и их роль в жизни и наследии поэта.\n\nДолгие годы Осип и Лиля будут отстаивать имя Маяковского и бороться за его память, но его уход не стал концом их истории.\nСовсем скоро Лиля и Осип Брик вступят в новую шпионскую игру\n\n\nНезаконное потребление наркотических средств, психотропных веществ, их аналогов причиняет вред здоровью, их незаконный оборот запрещен и влечет установленную законодательством ответственность."
            },
            "defaultAudioLanguage": "ru"
        },
        "contentDetails": {
            "duration": "PT41M22S",
            "dimension": "2d",
            "definition": "hd",
            "caption": "false",
            "licensedContent": true,
            "contentRating": {},
            "projection": "rectangular"
        },
        "statistics": {
            "viewCount": "171570",
            "likeCount": "13613",
            "favoriteCount": "0",
            "commentCount": "2058"
        }
    }
]